cmdpxl/__init__.py
cmdpxl/datatypes.py
cmdpxl/main.py
cmdpxl/terminal_io.py
cmdpxl-0.1.8.dist-info/LICENSE
cmdpxl-0.1.8.dist-info/METADATA
cmdpxl-0.1.8.dist-info/WHEEL
cmdpxl-0.1.8.dist-info/entry_points.txt
cmdpxl-0.1.8.dist-info/top_level.txt
cmdpxl-0.1.8.dist-info/RECORD
