Metadata-Version: 2.1
Name: cmdpxl
Version: 0.1.8
Summary: A totally practical command-line image editor
Home-page: https://github.com/knosmos/cmdpxl
Author: Jieruei Chang
Author-email: jierueic@gmail.com
License: MIT license
Keywords: cmdpxl,opencv,image-editor,terminal-based
Platform: UNKNOWN
Classifier: Development Status :: 2 - Pre-Alpha
Classifier: Intended Audience :: Developers
Classifier: License :: OSI Approved :: MIT License
Classifier: Natural Language :: English
Classifier: Programming Language :: Python :: 3
Classifier: Programming Language :: Python :: 3.6
Classifier: Programming Language :: Python :: 3.7
Classifier: Programming Language :: Python :: 3.8
Classifier: Programming Language :: Python :: 3.9
Requires-Python: >=3.6
Requires-Dist: opencv-python (==4.5.3.56)
Requires-Dist: numpy (==1.21.1)
Requires-Dist: click (==8.0.1)
